astc_encoder/__init__.py
astc_encoder/_encoder_avx2.pypy38-pp73-win_amd64.iobj
astc_encoder/_encoder_avx2.pypy38-pp73-win_amd64.ipdb
astc_encoder/_encoder_avx2.pypy38-pp73-win_amd64.pyd
astc_encoder/_encoder_none.pypy38-pp73-win_amd64.iobj
astc_encoder/_encoder_none.pypy38-pp73-win_amd64.ipdb
astc_encoder/_encoder_none.pypy38-pp73-win_amd64.pyd
astc_encoder/_encoder_sse2.pypy38-pp73-win_amd64.iobj
astc_encoder/_encoder_sse2.pypy38-pp73-win_amd64.ipdb
astc_encoder/_encoder_sse2.pypy38-pp73-win_amd64.pyd
astc_encoder/_encoder_sse41.pypy38-pp73-win_amd64.iobj
astc_encoder/_encoder_sse41.pypy38-pp73-win_amd64.ipdb
astc_encoder/_encoder_sse41.pypy38-pp73-win_amd64.pyd
astc_encoder/encoder.py
astc_encoder/encoder.pyi
astc_encoder/enum.py
astc_encoder/pil_codec.py
astc_encoder/py.typed
astc_encoder_py-0.1.12.dist-info/LICENSE
astc_encoder_py-0.1.12.dist-info/METADATA
astc_encoder_py-0.1.12.dist-info/WHEEL
astc_encoder_py-0.1.12.dist-info/top_level.txt
astc_encoder_py-0.1.12.dist-info/RECORD
